[
  {
    "smdCode": "5B",
    "package": "SOT-23",
    "deviceName": "BC807-25",
    "manufacturer": "General Semiconductor (Now Vishay)",
    "data": "PNP transistor",
    "datasheet": "www.s-manuals.com/pdf/datasheet/b/c/bc807%2C_bc808_general.pdf"
  },
  {
    "smdCode": "5B",
    "package": "SOT-23",
    "deviceName": "KST4123",
    "manufacturer": "Fairchild",
    "data": "NPN transistor",
    "datasheet": "www.s-manuals.com/pdf/datasheet/k/s/kst4123_fairchild.pdf"
  },
  {
    "smdCode": "5B",
    "package": "SOD-123F",
    "deviceName": "MM1Z10",
    "manufacturer": "Semtech",
    "data": "Zener diode",
    "datasheet": "www.s-manuals.com/pdf/datasheet/m/m/mm1z2v0-mm1z75_r0.1_semtech.pdf"
  },
  {
    "smdCode": "5B",
    "package": "SOT-523F",
    "deviceName": "MM5Z6V8",
    "manufacturer": "Fairchild",
    "data": "Zener diode",
    "datasheet": "www.s-manuals.com/pdf/datasheet/m/m/mm5z2v4-mmz5z75v_r1.0_fairchild.pdf"
  },
  {
    "smdCode": "5B**",
    "package": "SOT-23",
    "deviceName": "ST6205BS23RG",
    "manufacturer": "Stanson",
    "data": "LDO regulator",
    "datasheet": "www.s-manuals.com/pdf/datasheet/s/t/st6205_stanson.pdf"
  },
  {
    "smdCode": "5B**",
    "package": "SOT-323",
    "deviceName": "ST6205BS32RG",
    "manufacturer": "Stanson",
    "data": "LDO regulator",
    "datasheet": "www.s-manuals.com/pdf/datasheet/s/t/st6205_stanson.pdf"
  },
  {
    "smdCode": "5B-",
    "package": "SOT-23",
    "deviceName": "BC807-25",
    "manufacturer": "NXP",
    "data": "PNP transistor",
    "datasheet": "www.s-manuals.com/pdf/datasheet/b/c/bc327%2C_bc807%2C_bc807w_series_nxp.pdf"
  },
  {
    "smdCode": "5B-",
    "package": "SOT-323",
    "deviceName": "BC807-25W",
    "manufacturer": "NXP",
    "data": "PNP transistor",
    "datasheet": "www.s-manuals.com/pdf/datasheet/b/c/bc327%2C_bc807%2C_bc807w_series_nxp.pdf"
  },
  {
    "smdCode": "5B1",
    "package": "SOT-23",
    "deviceName": "BC807-25LT1G",
    "manufacturer": "ON",
    "data": "PNP transistor",
    "datasheet": "www.s-manuals.com/pdf/datasheet/b/c/bc807-16lt1g%2C_bc807-25lt1g%2C_bc807-40lt1g_on.pdf"
  },
  {
    "smdCode": "5BW",
    "package": "SOT-23",
    "deviceName": "BC807-25",
    "manufacturer": "NXP",
    "data": "PNP transistor",
    "datasheet": "www.s-manuals.com/pdf/datasheet/b/c/bc327%2C_bc807%2C_bc807w_series_nxp.pdf"
  },
  {
    "smdCode": "5BW",
    "package": "SOT-323",
    "deviceName": "BC807-25W",
    "manufacturer": "NXP",
    "data": "PNP transistor",
    "datasheet": "www.s-manuals.com/pdf/datasheet/b/c/bc327%2C_bc807%2C_bc807w_series_nxp.pdf"
  },
  {
    "smdCode": "5Bp",
    "package": "SOT-23",
    "deviceName": "BC807-25",
    "manufacturer": "NXP",
    "data": "PNP transistor",
    "datasheet": "www.s-manuals.com/pdf/datasheet/b/c/bc327%2C_bc807%2C_bc807w_series_nxp.pdf"
  },
  {
    "smdCode": "5Bp",
    "package": "SOT-323",
    "deviceName": "BC807-25W",
    "manufacturer": "NXP",
    "data": "PNP transistor",
    "datasheet": "www.s-manuals.com/pdf/datasheet/b/c/bc327%2C_bc807%2C_bc807w_series_nxp.pdf"
  },
  {
    "smdCode": "5Bt",
    "package": "SOT-23",
    "deviceName": "BC807-25",
    "manufacturer": "NXP",
    "data": "PNP transistor",
    "datasheet": "www.s-manuals.com/pdf/datasheet/b/c/bc327%2C_bc807%2C_bc807w_series_nxp.pdf"
  },
  {
    "smdCode": "5Bt",
    "package": "SOT-323",
    "deviceName": "BC807-25W",
    "manufacturer": "NXP",
    "data": "PNP transistor",
    "datasheet": "www.s-manuals.com/pdf/datasheet/b/c/bc327%2C_bc807%2C_bc807w_series_nxp.pdf"
  }
]