[
  {
    "smdCode": "WT",
    "package": "SOT-23",
    "deviceName": "2SK322",
    "manufacturer": "Hitachi",
    "data": "N-Channel JFET",
    "datasheet": "www.s-manuals.com/pdf/datasheet/2/s/2sk322_hitachi.pdf"
  },
  {
    "smdCode": "WT",
    "package": "SOD-123",
    "deviceName": "BZT52-C30",
    "manufacturer": "Panjit",
    "data": "Zener diode",
    "datasheet": "www.s-manuals.com/pdf/datasheet/b/z/bzt52-c2v4_series_r03_panjit.pdf"
  },
  {
    "smdCode": "WT",
    "package": "SOD-123",
    "deviceName": "BZT52C39",
    "manufacturer": "Diodes",
    "data": "Zener diode",
    "datasheet": "www.s-manuals.com/pdf/datasheet/b/z/bzt52c2v0-bzt52c51_r37-2_diodes.pdf"
  },
  {
    "smdCode": "WT",
    "package": "SOD-110",
    "deviceName": "BZX284-B3V9",
    "manufacturer": "NXP",
    "data": "Zener diode",
    "datasheet": "www.s-manuals.com/pdf/datasheet/b/z/bzx284_series_nxp.pdf"
  },
  {
    "smdCode": "WT",
    "package": "SOT-23",
    "deviceName": "BZX84C30-AU",
    "manufacturer": "Panjit",
    "data": "Zener diode",
    "datasheet": "www.s-manuals.com/pdf/datasheet/b/z/bzx84c2v4-au_series_r03_panjit.pdf"
  },
  {
    "smdCode": "WT",
    "package": "SOD-323",
    "deviceName": "PZU13B3A/DG",
    "manufacturer": "NXP",
    "data": "Zener diode",
    "datasheet": "www.s-manuals.com/pdf/datasheet/p/z/pzuxba_series_nxp.pdf"
  },
  {
    "smdCode": "WT",
    "package": "SMA",
    "deviceName": "SMAJ8.5CA",
    "manufacturer": "Littelfuse",
    "data": "TVS Diode",
    "datasheet": "www.s-manuals.com/pdf/datasheet/s/m/smaj_littelfuse.pdf"
  },
  {
    "smdCode": "WT***",
    "package": "SOT-23",
    "deviceName": "AX5505R35",
    "manufacturer": "Axelite",
    "data": "Step Up Converter",
    "datasheet": "www.s-manuals.com/pdf/datasheet/a/x/ax5505_r1.1_axelite.pdf"
  },
  {
    "smdCode": "WT-***",
    "package": "SOT-25",
    "deviceName": "RT8009PB",
    "manufacturer": "Richtek",
    "data": "Step-Down Converter",
    "datasheet": "www.s-manuals.com/pdf/datasheet/r/t/rt8009_richtek.pdf"
  },
  {
    "smdCode": "WT1",
    "package": "SOT-23",
    "deviceName": "BZX84-B9V1",
    "manufacturer": "NXP",
    "data": "Zener diode",
    "datasheet": "www.s-manuals.com/pdf/datasheet/b/z/bzx84_series_r6_nxp.pdf"
  },
  {
    "smdCode": "WT2",
    "package": "SOT-23",
    "deviceName": "BZX84-C27",
    "manufacturer": "NXP",
    "data": "Zener diode",
    "datasheet": "www.s-manuals.com/pdf/datasheet/b/z/bzx84_series_r6_nxp.pdf"
  },
  {
    "smdCode": "WT3",
    "package": "SOT-23",
    "deviceName": "BZX84-C2V4",
    "manufacturer": "NXP",
    "data": "Zener diode",
    "datasheet": "www.s-manuals.com/pdf/datasheet/b/z/bzx84_series_r6_nxp.pdf"
  },
  {
    "smdCode": "WT4",
    "package": "SOT-23",
    "deviceName": "BZX84-C2V7",
    "manufacturer": "NXP",
    "data": "Zener diode",
    "datasheet": "www.s-manuals.com/pdf/datasheet/b/z/bzx84_series_r6_nxp.pdf"
  },
  {
    "smdCode": "WT5",
    "package": "SOT-23",
    "deviceName": "BZX84-C30",
    "manufacturer": "NXP",
    "data": "Zener diode",
    "datasheet": "www.s-manuals.com/pdf/datasheet/b/z/bzx84_series_r6_nxp.pdf"
  },
  {
    "smdCode": "WT6",
    "package": "SOT-23",
    "deviceName": "BZX84-C33",
    "manufacturer": "NXP",
    "data": "Zener diode",
    "datasheet": "www.s-manuals.com/pdf/datasheet/b/z/bzx84_series_r6_nxp.pdf"
  },
  {
    "smdCode": "WT7",
    "package": "SOT-23",
    "deviceName": "BZX84-C36",
    "manufacturer": "NXP",
    "data": "Zener diode",
    "datasheet": "www.s-manuals.com/pdf/datasheet/b/z/bzx84_series_r6_nxp.pdf"
  },
  {
    "smdCode": "WT8",
    "package": "SOT-23",
    "deviceName": "BZX84-C39",
    "manufacturer": "NXP",
    "data": "Zener diode",
    "datasheet": "www.s-manuals.com/pdf/datasheet/b/z/bzx84_series_r6_nxp.pdf"
  },
  {
    "smdCode": "WT9",
    "package": "SOT-23",
    "deviceName": "BZX84-C3V0",
    "manufacturer": "NXP",
    "data": "Zener diode",
    "datasheet": "www.s-manuals.com/pdf/datasheet/b/z/bzx84_series_r6_nxp.pdf"
  },
  {
    "smdCode": "WT=***",
    "package": "SOT-25",
    "deviceName": "RT8009GB",
    "manufacturer": "Richtek",
    "data": "Step-Down Converter",
    "datasheet": "www.s-manuals.com/pdf/datasheet/r/t/rt8009_richtek.pdf"
  }
]