[
  {
    "smdCode": "Z7",
    "package": "SOT-89",
    "deviceName": "BZV49C8V2",
    "manufacturer": "Zetex (Now Diodes)",
    "data": "Zener diode",
    "datasheet": "www.s-manuals.com/pdf/datasheet/b/z/bzv49_series_zetex.pdf"
  },
  {
    "smdCode": "Z7",
    "package": "SOT-23",
    "deviceName": "BZX84C8V2",
    "manufacturer": "Taitron",
    "data": "Zener diode",
    "datasheet": "www.s-manuals.com/pdf/datasheet/t/z/tzt2v4aw-tzt51aw%2C_tzt2v4cw-tzt51cw%2C_bzx84c2c4-bzx84c75_20130830_taitron.pdf"
  },
  {
    "smdCode": "Z7",
    "package": "SOT-23",
    "deviceName": "BZX84C8V2-V",
    "manufacturer": "Vishay",
    "data": "Zener diode",
    "datasheet": "www.s-manuals.com/pdf/datasheet/b/z/bzx84-v-series_vishay.pdf"
  },
  {
    "smdCode": "Z7",
    "package": "SOT-23",
    "deviceName": "BZX84C8V2LT1G",
    "manufacturer": "ON",
    "data": "Zener diode",
    "datasheet": "www.s-manuals.com/pdf/datasheet/b/z/bzx84bxxxlt1g%2C_bzx84cxxxlt1g%2C_szbzx84bxxxlt1g%2C_szbzx84cxxxlt1g_on.pdf"
  },
  {
    "smdCode": "Z7",
    "package": "EMT6",
    "deviceName": "EMZ7",
    "manufacturer": "ROHM",
    "data": "NPN + PNP transistors",
    "datasheet": "www.s-manuals.com/pdf/datasheet/e/m/emz7%2C_umz7n_rohm.pdf"
  },
  {
    "smdCode": "Z7",
    "package": "SOD-323",
    "deviceName": "PDZ4.7B",
    "manufacturer": "NXP",
    "data": "Zener diode",
    "datasheet": "www.s-manuals.com/pdf/datasheet/p/d/pdz-b_series_nxp.pdf"
  },
  {
    "smdCode": "Z7",
    "package": "SOT-23",
    "deviceName": "SZBZX84C8V2LT1G",
    "manufacturer": "ON",
    "data": "Zener diode",
    "datasheet": "www.s-manuals.com/pdf/datasheet/b/z/bzx84bxxxlt1g%2C_bzx84cxxxlt1g%2C_szbzx84bxxxlt1g%2C_szbzx84cxxxlt1g_on.pdf"
  },
  {
    "smdCode": "Z7",
    "package": "SOT-363",
    "deviceName": "UMZ7N",
    "manufacturer": "ROHM",
    "data": "NPN + PNP transistors",
    "datasheet": "www.s-manuals.com/pdf/datasheet/e/m/emz7%2C_umz7n_rohm.pdf"
  },
  {
    "smdCode": "Z7-",
    "package": "SOT-23",
    "deviceName": "BZX84-C8V2",
    "manufacturer": "NXP",
    "data": "Zener diode",
    "datasheet": "www.s-manuals.com/pdf/datasheet/b/z/bzx84_series_r6_nxp.pdf"
  },
  {
    "smdCode": "Z70",
    "package": "SOT-23",
    "deviceName": "BZX84-B16",
    "manufacturer": "NXP",
    "data": "Zener diode",
    "datasheet": "www.s-manuals.com/pdf/datasheet/b/z/bzx84_series_nxp.pdf"
  },
  {
    "smdCode": "Z70",
    "package": "SOT-23",
    "deviceName": "BZX84B16-V",
    "manufacturer": "Vishay",
    "data": "Zener diode",
    "datasheet": "www.s-manuals.com/pdf/datasheet/b/z/bzx84-v-series_vishay.pdf"
  },
  {
    "smdCode": "Z71",
    "package": "SOT-23",
    "deviceName": "BZX84-B18",
    "manufacturer": "NXP",
    "data": "Zener diode",
    "datasheet": "www.s-manuals.com/pdf/datasheet/b/z/bzx84_series_nxp.pdf"
  },
  {
    "smdCode": "Z71",
    "package": "SOT-23",
    "deviceName": "BZX84B18-V",
    "manufacturer": "Vishay",
    "data": "Zener diode",
    "datasheet": "www.s-manuals.com/pdf/datasheet/b/z/bzx84-v-series_vishay.pdf"
  },
  {
    "smdCode": "Z72",
    "package": "SOT-23",
    "deviceName": "BZX84-B20",
    "manufacturer": "NXP",
    "data": "Zener diode",
    "datasheet": "www.s-manuals.com/pdf/datasheet/b/z/bzx84_series_nxp.pdf"
  },
  {
    "smdCode": "Z72",
    "package": "SOT-23",
    "deviceName": "BZX84B20-V",
    "manufacturer": "Vishay",
    "data": "Zener diode",
    "datasheet": "www.s-manuals.com/pdf/datasheet/b/z/bzx84-v-series_vishay.pdf"
  },
  {
    "smdCode": "Z73",
    "package": "SOT-23",
    "deviceName": "BZX84-B22",
    "manufacturer": "NXP",
    "data": "Zener diode",
    "datasheet": "www.s-manuals.com/pdf/datasheet/b/z/bzx84_series_nxp.pdf"
  },
  {
    "smdCode": "Z73",
    "package": "SOT-23",
    "deviceName": "BZX84B22-V",
    "manufacturer": "Vishay",
    "data": "Zener diode",
    "datasheet": "www.s-manuals.com/pdf/datasheet/b/z/bzx84-v-series_vishay.pdf"
  },
  {
    "smdCode": "Z74",
    "package": "SOT-23",
    "deviceName": "BZX84-B24",
    "manufacturer": "NXP",
    "data": "Zener diode",
    "datasheet": "www.s-manuals.com/pdf/datasheet/b/z/bzx84_series_nxp.pdf"
  },
  {
    "smdCode": "Z74",
    "package": "SOT-23",
    "deviceName": "BZX84B24-V",
    "manufacturer": "Vishay",
    "data": "Zener diode",
    "datasheet": "www.s-manuals.com/pdf/datasheet/b/z/bzx84-v-series_vishay.pdf"
  },
  {
    "smdCode": "Z75",
    "package": "SOT-23",
    "deviceName": "BZX84-B27",
    "manufacturer": "NXP",
    "data": "Zener diode",
    "datasheet": "www.s-manuals.com/pdf/datasheet/b/z/bzx84_series_nxp.pdf"
  },
  {
    "smdCode": "Z75",
    "package": "SOT-23",
    "deviceName": "BZX84B27-V",
    "manufacturer": "Vishay",
    "data": "Zener diode",
    "datasheet": "www.s-manuals.com/pdf/datasheet/b/z/bzx84-v-series_vishay.pdf"
  },
  {
    "smdCode": "Z76",
    "package": "SOT-23",
    "deviceName": "BZX84-B30",
    "manufacturer": "NXP",
    "data": "Zener diode",
    "datasheet": "www.s-manuals.com/pdf/datasheet/b/z/bzx84_series_nxp.pdf"
  },
  {
    "smdCode": "Z76",
    "package": "SOT-23",
    "deviceName": "BZX84B30-V",
    "manufacturer": "Vishay",
    "data": "Zener diode",
    "datasheet": "www.s-manuals.com/pdf/datasheet/b/z/bzx84-v-series_vishay.pdf"
  },
  {
    "smdCode": "Z77",
    "package": "SOT-23",
    "deviceName": "BZX84-B33",
    "manufacturer": "NXP",
    "data": "Zener diode",
    "datasheet": "www.s-manuals.com/pdf/datasheet/b/z/bzx84_series_nxp.pdf"
  },
  {
    "smdCode": "Z77",
    "package": "SOT-23",
    "deviceName": "BZX84B33-V",
    "manufacturer": "Vishay",
    "data": "Zener diode",
    "datasheet": "www.s-manuals.com/pdf/datasheet/b/z/bzx84-v-series_vishay.pdf"
  },
  {
    "smdCode": "Z78",
    "package": "SOT-23",
    "deviceName": "BZX84-B36",
    "manufacturer": "NXP",
    "data": "Zener diode",
    "datasheet": "www.s-manuals.com/pdf/datasheet/b/z/bzx84_series_nxp.pdf"
  },
  {
    "smdCode": "Z78",
    "package": "SOT-23",
    "deviceName": "BZX84B36-V",
    "manufacturer": "Vishay",
    "data": "Zener diode",
    "datasheet": "www.s-manuals.com/pdf/datasheet/b/z/bzx84-v-series_vishay.pdf"
  },
  {
    "smdCode": "Z79",
    "package": "SOT-23",
    "deviceName": "BZX84-B39",
    "manufacturer": "NXP",
    "data": "Zener diode",
    "datasheet": "www.s-manuals.com/pdf/datasheet/b/z/bzx84_series_nxp.pdf"
  },
  {
    "smdCode": "Z79",
    "package": "SOT-23",
    "deviceName": "BZX84B39-V",
    "manufacturer": "Vishay",
    "data": "Zener diode",
    "datasheet": "www.s-manuals.com/pdf/datasheet/b/z/bzx84-v-series_vishay.pdf"
  },
  {
    "smdCode": "Z7W",
    "package": "SOT-23",
    "deviceName": "BZX84-C8V2",
    "manufacturer": "NXP",
    "data": "Zener diode",
    "datasheet": "www.s-manuals.com/pdf/datasheet/b/z/bzx84_series_r6_nxp.pdf"
  },
  {
    "smdCode": "Z7Z",
    "package": "SOT-323",
    "deviceName": "CMSZDA8V2",
    "manufacturer": "Central",
    "data": "Zener diodes",
    "datasheet": "www.s-manuals.com/pdf/datasheet/c/m/cmszda_series_central.pdf"
  },
  {
    "smdCode": "Z7p",
    "package": "SOT-23",
    "deviceName": "BZX84-C8V2",
    "manufacturer": "NXP",
    "data": "Zener diode",
    "datasheet": "www.s-manuals.com/pdf/datasheet/b/z/bzx84_series_r6_nxp.pdf"
  },
  {
    "smdCode": "Z7t",
    "package": "SOT-23",
    "deviceName": "BZX84-C8V2",
    "manufacturer": "NXP",
    "data": "Zener diode",
    "datasheet": "www.s-manuals.com/pdf/datasheet/b/z/bzx84_series_r6_nxp.pdf"
  }
]